ormar/__init__.py
ormar/decorators/__init__.py
ormar/decorators/signals.py
ormar/exceptions.py
ormar/fields/__init__.py
ormar/fields/base.py
ormar/fields/constraints.py
ormar/fields/foreign_key.py
ormar/fields/many_to_many.py
ormar/fields/model_fields.py
ormar/fields/parsers.py
ormar/fields/referential_actions.py
ormar/fields/sqlalchemy_encrypted.py
ormar/fields/sqlalchemy_uuid.py
ormar/fields/through_field.py
ormar/models/__init__.py
ormar/models/descriptors/__init__.py
ormar/models/descriptors/descriptors.py
ormar/models/excludable.py
ormar/models/helpers/__init__.py
ormar/models/helpers/models.py
ormar/models/helpers/pydantic.py
ormar/models/helpers/related_names_validation.py
ormar/models/helpers/relations.py
ormar/models/helpers/sqlalchemy.py
ormar/models/helpers/validation.py
ormar/models/metaclass.py
ormar/models/mixins/__init__.py
ormar/models/mixins/alias_mixin.py
ormar/models/mixins/excludable_mixin.py
ormar/models/mixins/merge_mixin.py
ormar/models/mixins/pydantic_mixin.py
ormar/models/mixins/relation_mixin.py
ormar/models/mixins/save_mixin.py
ormar/models/model.py
ormar/models/model_row.py
ormar/models/modelproxy.py
ormar/models/newbasemodel.py
ormar/models/ormar_config.py
ormar/models/quick_access_views.py
ormar/models/traversible.py
ormar/models/utils.py
ormar/protocols/__init__.py
ormar/protocols/queryset_protocol.py
ormar/protocols/relation_protocol.py
ormar/py.typed
ormar/queryset/__init__.py
ormar/queryset/actions/__init__.py
ormar/queryset/actions/filter_action.py
ormar/queryset/actions/order_action.py
ormar/queryset/actions/query_action.py
ormar/queryset/actions/select_action.py
ormar/queryset/clause.py
ormar/queryset/field_accessor.py
ormar/queryset/join.py
ormar/queryset/queries/__init__.py
ormar/queryset/queries/filter_query.py
ormar/queryset/queries/limit_query.py
ormar/queryset/queries/offset_query.py
ormar/queryset/queries/order_query.py
ormar/queryset/queries/prefetch_query.py
ormar/queryset/queries/query.py
ormar/queryset/queryset.py
ormar-0.21.0.dist-info/LICENSE.md
ormar-0.21.0.dist-info/METADATA
ormar-0.21.0.dist-info/WHEEL
ormar-0.21.0.dist-info/RECORD
