Metadata-Version: 2.1
Name: ormar
Version: 0.21.0
Summary: An async ORM with fastapi in mind and pydantic validation.
Home-page: https://github.com/collerek/ormar
License: MIT
Keywords: orm,sqlalchemy,fastapi,pydantic,databases,async,alembic
Author: Radosław Drążkiewicz
Author-email: collerek@gmail.com
Requires-Python: >=3.9.0,<4.0.0
Classifier: Development Status :: 4 - Beta
Classifier: Environment :: Web Environment
Classifier: Framework :: AsyncIO
Classifier: Intended Audience :: Developers
Classifier: License :: OSI Approved :: MIT License
Classifier: Operating System :: OS Independent
Classifier: Programming Language :: Python :: 3
Classifier: Programming Language :: Python :: 3.9
Classifier: Programming Language :: Python :: 3.10
Classifier: Programming Language :: Python :: 3.11
Classifier: Programming Language :: Python :: 3.12
Classifier: Programming Language :: Python :: 3.13
Classifier: Programming Language :: Python :: 3 :: Only
Classifier: Programming Language :: Python :: 3.8
Classifier: Topic :: Internet :: WWW/HTTP
Provides-Extra: aiopg
Provides-Extra: all
Provides-Extra: crypto
Provides-Extra: mysql
Provides-Extra: orjson
Provides-Extra: postgres
Provides-Extra: postgresql
Provides-Extra: sqlite
Requires-Dist: PyMySQL (>=1.1.0,<2.0.0) ; extra == "mysql" or extra == "all"
Requires-Dist: SQLAlchemy[asyncio] (>=2.0.40,<3.0.0)
Requires-Dist: aiomysql (>=0.1.0) ; extra == "mysql" or extra == "all"
Requires-Dist: aiopg (>=1.3.3,<2.0.0) ; extra == "aiopg" or extra == "all"
Requires-Dist: aiosqlite (>=0.19,<0.21) ; extra == "sqlite" or extra == "all"
Requires-Dist: asyncpg (>=0.28,<0.31) ; extra == "postgresql" or extra == "postgres" or extra == "all"
Requires-Dist: cryptography (>=41.0.3,<44.0.0) ; extra == "crypto" or extra == "all"
Requires-Dist: databases (>=0.9.0,<0.10.0)
Requires-Dist: mysqlclient (>=2.1.0,<3.0.0) ; extra == "all"
Requires-Dist: orjson (>=3.6.4) ; extra == "orjson" or extra == "all"
Requires-Dist: psycopg2-binary (>=2.9.1,<3.0.0) ; extra == "postgresql" or extra == "postgres" or extra == "aiopg" or extra == "all"
Requires-Dist: pydantic (>=2.11.9,<3.0.0)
Project-URL: Documentation, https://collerek.github.io/ormar/
Project-URL: Repository, https://github.com/collerek/ormar
